pygt3x/__init__.py
pygt3x/activity_payload.py
pygt3x/calibration.py
pygt3x/components.py
pygt3x/reader.py
pygt3x-0.7.1.dist-info/METADATA
pygt3x-0.7.1.dist-info/WHEEL
pygt3x-0.7.1.dist-info/licenses/LICENSE
pygt3x-0.7.1.dist-info/RECORD
