Metadata-Version: 2.4
Name: pygt3x
Version: 0.7.1
Summary: Python module for reading GT3X/AGDC file format data
Project-URL: Repository, https://github.com/actigraph/pygt3x
Author-email: Mark Fogle <mark.fogle@theactigraph.com>
Maintainer-email: Ali Neishabouri <ali.neishabouri@theactigraph.com>
License-Expression: GPL-3.0-or-later
License-File: LICENSE
Requires-Python: <=3.13,>3.9
Requires-Dist: numpy>=1.21.2
Requires-Dist: pandas>=1.2.5
